bioluigi/__init__.py
bioluigi/cli.py
bioluigi/config.py
bioluigi/local_target.py
bioluigi/scheduled_external_program.py
bioluigi/schedulers.py
bioluigi/tasks/__init__.py
bioluigi/tasks/bcftools.py
bioluigi/tasks/cellranger.py
bioluigi/tasks/cutadapt.py
bioluigi/tasks/fastqc.py
bioluigi/tasks/multiqc.py
bioluigi/tasks/rsem.py
bioluigi/tasks/samtools.py
bioluigi/tasks/sratoolkit.py
bioluigi/tasks/star.py
bioluigi/tasks/utils.py
bioluigi/tasks/vep.py
bioluigi-0.3.0.dist-info/licenses/LICENSE
bioluigi-0.3.0.dist-info/METADATA
bioluigi-0.3.0.dist-info/WHEEL
bioluigi-0.3.0.dist-info/entry_points.txt
bioluigi-0.3.0.dist-info/top_level.txt
bioluigi-0.3.0.dist-info/RECORD
