Metadata-Version: 2.4
Name: bioluigi
Version: 0.3.0
Summary: Reusable and maintained Luigi tasks to incorporate in bioinformatics pipelines
Author-email: Guillaume Poirier-Morency <poirigui@msl.ubc.ca>
License-Expression: Apache-2.0
Project-URL: homepage, https://github.com/pavlidisLab/bioluigi
Requires-Python: >=3.9
License-File: LICENSE
Requires-Dist: click
Requires-Dist: luigi
Requires-Dist: python-daemon<3.0.0
Requires-Dist: requests
Dynamic: license-file
